setup.py
pippackagepoc/__init__.py
pippackagepoc/text.py
pippackagepoc.egg-info/PKG-INFO
pippackagepoc.egg-info/SOURCES.txt
pippackagepoc.egg-info/dependency_links.txt
pippackagepoc.egg-info/not-zip-safe
pippackagepoc.egg-info/requires.txt
pippackagepoc.egg-info/top_level.txt