Metadata-Version: 1.0
Name: pippackagepoc
Version: 1.1
Summary: The funniest joke in the world
Home-page: UNKNOWN
Author: Flying Circus
Author-email: flyingcircus@example.com
License: MIT
Platform: UNKNOWN
